pytest_openfiles/__init__.py
pytest_openfiles/plugin.py
pytest_openfiles/version.py
pytest_openfiles-0.6.0.dist-info/LICENSE.rst
pytest_openfiles-0.6.0.dist-info/METADATA
pytest_openfiles-0.6.0.dist-info/WHEEL
pytest_openfiles-0.6.0.dist-info/entry_points.txt
pytest_openfiles-0.6.0.dist-info/top_level.txt
pytest_openfiles-0.6.0.dist-info/RECORD
