Metadata-Version: 2.1
Name: pytest-openfiles
Version: 0.6.0
Summary: Pytest plugin for detecting inadvertent open file handles
Home-page: https://github.com/astropy/pytest-openfiles
Author: The Astropy Developers
Author-email: astropy.team@gmail.com
License: BSD
Keywords: detect,open,file,handle,psutil,pytest,py.test
Classifier: Development Status :: 3 - Alpha
Classifier: Framework :: Pytest
Classifier: Intended Audience :: Developers
Classifier: License :: OSI Approved :: BSD License
Classifier: Operating System :: OS Independent
Classifier: Programming Language :: Python
Classifier: Programming Language :: Python :: 3
Classifier: Programming Language :: Python :: 3 :: Only
Classifier: Programming Language :: Python :: 3.7
Classifier: Programming Language :: Python :: 3.8
Classifier: Programming Language :: Python :: 3.9
Classifier: Programming Language :: Python :: 3.10
Classifier: Programming Language :: Python :: 3.11
Classifier: Programming Language :: Python :: Implementation :: CPython
Classifier: Topic :: Software Development :: Testing
Classifier: Topic :: Utilities
Requires-Python: >=3.7
License-File: LICENSE.rst
Requires-Dist: packaging
Requires-Dist: pytest >=4.6
Requires-Dist: psutil
